kozai/__init__.py
kozai/mlflow/__init__.py
kozai/mlflow/artifact_repository.py
kozai/mlflow/notebook_run_context.py
kozai_mlflow-0.7.2.dist-info/METADATA
kozai_mlflow-0.7.2.dist-info/WHEEL
kozai_mlflow-0.7.2.dist-info/entry_points.txt
kozai_mlflow-0.7.2.dist-info/top_level.txt
kozai_mlflow-0.7.2.dist-info/RECORD
