Metadata-Version: 2.1
Name: kozai-mlflow
Version: 0.7.2
Summary: MLflow for integrated kozai environments
Home-page: https://gitlab.mantelgroup.com.au/
Author: Lucas Sargent
Author-email: lucas.sargent@eliiza.com.au
Project-URL: Bug Tracker, https://gitlab.mantelgroup.com.au/
Keywords: kozai
Classifier: Programming Language :: Python :: 3
Classifier: Operating System :: OS Independent
Requires-Python: >=3.7
Requires-Dist: mlflow-skinny (==1.28.0)
Requires-Dist: azure-identity (==1.10.0)
Requires-Dist: azure-storage-blob (==12.13.1)
Provides-Extra: tests
Requires-Dist: pytest (==6.2.4) ; extra == 'tests'
